{
  "description": [
    "Chain-in website: http://chain-in.org/\n",
    "\n",
    "Attendees are expected to learn real stuff on blockchains starting from technical and not ending with social aspects. Speakers are gradually added to the website; the final list will ensure having a good diversity of blockchain-related topics like CS, business, economics, law, etc.\n",
    "\n",
    "Experts at the venue and speakers will also be invited to a rounded-table meeting to discuss the future of the technology.\n",
    "\n",
    "An attendee?\n",
    "Reserve your seat for one or two days according to your interest here: http://chain-in.org/register.php.\n",
    "\n",
    "A speaker?\n",
    "Suggest your talk here: http://chain-in.org/speaker.php\n",
    "\n",
    "A sponsor?\n",
    "See sponsorship plans here: http://chain-in.org/sponsorship.php"
  ],
  "end_date": "2018-07-09",
  "location": null,
  "name": "Chain-in Conference in Porto",
  "rrule": null,
  "start_date": "2018-07-09",
  "url": "https://www.meetup.com/Chain-in-Blockchain-Cryptocurrency-Conference/events/249631229/"
}