{
  "description": [
    "On May 26th, Mindera will open its doors and welcome everyone who wants to hear and learn about Frontend.\n",
    "Get to know us a little bit better - the technologies that passionate us and how we work.\u00a0\n",
    "This time, we also have a surprise: invited speakers who will come and share their knowledge too!\n",
    "We dare you to spend your saturday with us, participate in our talks and workshop ;)\n",
    "\n",
    "Check the agenda bellow:\n",
    "11:00 - 11:30 - Welcome to Mindera (check-in)\n",
    "11:30 - Talk (to be announced)\n",
    "12:00 - Talk\u00a0(to be announced)\n",
    "12:30 - Talk\u00a0(to be announced)\n",
    "13:00 - Lunch\n",
    "14:00 - Talk\u00a0(to be announced)\n",
    "14:00 -\u00a0 Workshop: \u201cUp and running with react and graphql\u201d\n",
    "14:30 - Talk\u00a0(to be announced)\n",
    "15:00 - Talk\u00a0(to be announced)\n",
    "15:30 - Talk\u00a0(to be announced)\n",
    "16:00 - Closing\n",
    "\n",
    "Meet you there?\n",
    "PS. If you want to join the workshop, chose \"Mindera | Frontend Tech Day + Workshop\" ticket and don't forget to bring you computer! Install Node.JS and if you are a Window's friend, make sure you have git bash terminal!"
  ],
  "end_date": "2018-05-26",
  "location": "Mindera",
  "name": "Mindera | Frontend Tech Day",
  "rrule": null,
  "start_date": "2018-05-26",
  "url": "https://www.eventbrite.pt/e/bilhetes-mindera-frontend-tech-day-45863143898?aff=ebapi"
}