{
  "description": [
    "Hello all!\n",
    "\n",
    "It's been a while since we organized the last Porto Big Data meetup, and it's time to restart the data engagement.\n",
    "\n",
    "As such we are holding another meetup, and will have great speakers from Google and Dataiku.\n",
    "\n",
    "Talk 1: From Zero to Machine Learning on Google Cloud\n",
    "Tiago S\u00e1 (https://www.linkedin.com/in/tiagosa/)\n",
    "Customer Engineer at Google Cloud Portugal\n",
    "\n",
    "----------\n",
    "\n",
    "Talk 2: Customer Segmentation, Churn Detection: How to leverage Advanced Analytics for Increased Customer Knowledge\n",
    "Lynn Rachwan (https://www.linkedin.com/in/lynn-rachwan-dataiku)\n",
    "Business Developer at Dataiku\n",
    "\n",
    "We are also gonna have some pizzas for the networking session.\n",
    "\n",
    "Hoping to see you there,\n",
    "Rui Ramos"
  ],
  "end_date": "2018-10-01",
  "location": "Farfetch",
  "name": "Porto Big Data - 3rd Meetup",
  "rrule": null,
  "start_date": "2018-10-01",
  "url": "https://www.meetup.com/Porto-Big-Data/events/254882622/"
}