{
  "description": [
    "Uma semana inteiramente dedicada \u00e0 metodologia do Design Thinking. \n",
    "Dia 8 \u2013 Servi\u00e7os\n",
    "\u2013 Susana Ribeiro (\u00a0www.urwelcome2visit.pt/\u00a0) \u2013 PT\n",
    "\u2013 Pablo L\u00f3pez (\u00a0www.exga3d.com/\u00a0) \u2013 ES\n",
    "\u2013 Katja Tschimmel (\u00a0www.mindshake.pt/\u00a0) \u2013 PT \n"
  ],
  "end_date": "2018-10-08",
  "location": null,
  "name": "WOW DESIGN THINKING WEEK - Servi\u00e7os",
  "rrule": null,
  "start_date": "2018-10-08",
  "url": "http://scaleupporto.pt/event/wow-design-thinking-week-servicos/"
}