{
  "description": [
    "Porto Testers Meetup is a group of friends that decided to contribute to the community by starting to organize events where we could gather everyone interested in all the topics regarding testing. \n",
    "From the local meetup events to the \u201creal deal\u201d, PTM Conf is our contribution to the community in the form of a 1-day conference. \n"
  ],
  "end_date": "2018-06-16",
  "location": null,
  "name": "PTM Conf 2018",
  "rrule": null,
  "start_date": "2018-06-16",
  "url": "http://scaleupporto.pt/event/ptm-conf-2018/"
}